top_100/__init__.py
top_100/extract_urls.py
top_100/main.py
top_100/requirements.txt
top_100-0.1.4.dist-info/LICENSE
top_100-0.1.4.dist-info/METADATA
top_100-0.1.4.dist-info/WHEEL
top_100-0.1.4.dist-info/RECORD
