Metadata-Version: 2.1
Name: top_100
Version: 0.1.4
Summary: Top 100 Visited Sites Web Scraper
Author: reinaldopenno
Author-email: rapenno@gmail.com
Requires-Python: >=3.11,<4.0
Classifier: Programming Language :: Python :: 3
Classifier: Programming Language :: Python :: 3.11
Classifier: Programming Language :: Python :: 3.12
Requires-Dist: beautifulsoup4 (==4.12.2)
Requires-Dist: requests (==2.31.0)
